[
    {
        "letter": "A",
        "showsList": [
                {   
                "id": 1,
                "showCover": "",
                "showName": "The Morning Sports",
                "episodeList": 12
            },
            {   
                "i`d": 2,
                "showCover": "",
                "showName": "The Morning Sports",
                "episodeList": 12
            },
            {   
                "id": 3,
                "showCover": "",
                "showName": "The Morning Sports",
                "episodeList": 12
            }, 
            {   
                "id": 4,
                "showCover": "",
                "showName": "The Morning Sports",
                "episodeList": 12
            }, 
            {   
                "id": 5,
                "showCover": "",
                "showName": "The Morning Sports",
                "episodeList": 12
            }
        ]
    }
]